genai_otel/__init__.py
genai_otel/__version__.py
genai_otel/auto_instrument.py
genai_otel/cli.py
genai_otel/config.py
genai_otel/cost_calculator.py
genai_otel/cost_enriching_exporter.py
genai_otel/cost_enrichment_processor.py
genai_otel/exceptions.py
genai_otel/gpu_metrics.py
genai_otel/gpu_metrics_amd.py
genai_otel/litellm_span_enrichment_processor.py
genai_otel/llm_pricing.json
genai_otel/logging_config.py
genai_otel/mcp_span_enrichment_processor.py
genai_otel/metrics.py
genai_otel/py.typed
genai_otel/server_metrics.py
genai_otel/smolagents_span_enrichment_processor.py
genai_otel/evaluation/__init__.py
genai_otel/evaluation/bias_detector.py
genai_otel/evaluation/config.py
genai_otel/evaluation/hallucination_detector.py
genai_otel/evaluation/pii_detector.py
genai_otel/evaluation/prompt_injection_detector.py
genai_otel/evaluation/restricted_topics_detector.py
genai_otel/evaluation/span_processor.py
genai_otel/evaluation/toxicity_detector.py
genai_otel/instrumentors/__init__.py
genai_otel/instrumentors/anthropic_instrumentor.py
genai_otel/instrumentors/anyscale_instrumentor.py
genai_otel/instrumentors/autogen_instrumentor.py
genai_otel/instrumentors/aws_bedrock_instrumentor.py
genai_otel/instrumentors/azure_openai_instrumentor.py
genai_otel/instrumentors/base.py
genai_otel/instrumentors/bedrock_agents_instrumentor.py
genai_otel/instrumentors/cohere_instrumentor.py
genai_otel/instrumentors/crewai_instrumentor.py
genai_otel/instrumentors/dspy_instrumentor.py
genai_otel/instrumentors/google_ai_instrumentor.py
genai_otel/instrumentors/groq_instrumentor.py
genai_otel/instrumentors/guardrails_ai_instrumentor.py
genai_otel/instrumentors/haystack_instrumentor.py
genai_otel/instrumentors/huggingface_instrumentor.py
genai_otel/instrumentors/hyperbolic_instrumentor.py
genai_otel/instrumentors/instructor_instrumentor.py
genai_otel/instrumentors/langchain_instrumentor.py
genai_otel/instrumentors/langgraph_instrumentor.py
genai_otel/instrumentors/llamaindex_instrumentor.py
genai_otel_instrument-0.1.31.dist-info/licenses/LICENSE
genai_otel_instrument-0.1.31.dist-info/METADATA
genai_otel_instrument-0.1.31.dist-info/WHEEL
genai_otel_instrument-0.1.31.dist-info/entry_points.txt
genai_otel_instrument-0.1.31.dist-info/top_level.txt
genai_otel_instrument-0.1.31.dist-info/RECORD
