Metadata-Version: 2.4
Name: genai-otel-instrument
Version: 0.1.31
Summary: Comprehensive OpenTelemetry auto-instrumentation for LLM/GenAI applications
Author-email: Kshitij Thakkar <kshitijthakkar@rocketmail.com>
License: AGPL-3.0-or-later
Project-URL: Homepage, https://github.com/Mandark-droid/genai_otel_instrument
Project-URL: Repository, https://github.com/Mandark-droid/genai_otel_instrument
Project-URL: Documentation, https://github.com/Mandark-droid/genai_otel_instrument#readme
Project-URL: Issues, https://github.com/Mandark-droid/genai_otel_instrument/issues
Project-URL: Changelog, https://github.com/Mandark-droid/genai_otel_instrument/blob/main/CHANGELOG.md
Keywords: opentelemetry,observability,llm,genai,instrumentation,tracing,metrics,monitoring
Classifier: Development Status :: 4 - Beta
Classifier: Intended Audience :: Developers
Classifier: Topic :: Software Development :: Libraries :: Python Modules
Classifier: Topic :: System :: Monitoring
Classifier: License :: OSI Approved :: GNU Affero General Public License v3 or later (AGPLv3+)
Classifier: Operating System :: OS Independent
Classifier: Programming Language :: Python :: 3
Classifier: Programming Language :: Python :: 3.9
Classifier: Programming Language :: Python :: 3.10
Classifier: Programming Language :: Python :: 3.11
Classifier: Programming Language :: Python :: 3.12
Requires-Python: >=3.9
License-File: LICENSE
Requires-Dist: opentelemetry-api<2.0.0,>=1.20.0
Requires-Dist: opentelemetry-sdk<2.0.0,>=1.20.0
Requires-Dist: opentelemetry-instrumentation>=0.41b0
Requires-Dist: opentelemetry-semantic-conventions<1.0.0,>=0.45b0
Requires-Dist: opentelemetry-exporter-otlp>=1.20.0
Requires-Dist: opentelemetry-instrumentation-requests>=0.41b0
Requires-Dist: opentelemetry-instrumentation-httpx>=0.41b0
Requires-Dist: requests>=2.20.0
Requires-Dist: wrapt>=1.14.0
Requires-Dist: httpx>=0.23.0
Requires-Dist: opentelemetry-instrumentation-mysql>=0.41b0
Requires-Dist: mysql-connector-python>=9.1.0
Requires-Dist: opentelemetry-instrumentation-psycopg2>=0.41b0
Requires-Dist: psycopg2-binary>=2.9.0
Requires-Dist: opentelemetry-instrumentation-redis>=0.41b0
Requires-Dist: redis
Requires-Dist: opentelemetry-instrumentation-pymongo>=0.41b0
Requires-Dist: pymongo
Requires-Dist: opentelemetry-instrumentation-sqlalchemy>=0.41b0
Requires-Dist: sqlalchemy>=1.4.0
Requires-Dist: opentelemetry-instrumentation-kafka-python>=0.41b0
Requires-Dist: kafka-python
Provides-Extra: openinference
Requires-Dist: openinference-instrumentation==0.1.31; extra == "openinference"
Requires-Dist: openinference-instrumentation-litellm==0.1.19; extra == "openinference"
Requires-Dist: openinference-instrumentation-mcp==1.3.0; extra == "openinference"
Requires-Dist: openinference-instrumentation-smolagents==0.1.11; extra == "openinference"
Requires-Dist: litellm>=1.0.0; extra == "openinference"
Provides-Extra: evaluation
Requires-Dist: presidio-analyzer>=2.2.0; extra == "evaluation"
Requires-Dist: presidio-anonymizer>=2.2.0; extra == "evaluation"
Requires-Dist: spacy>=3.0.0; extra == "evaluation"
Requires-Dist: detoxify>=0.5.0; extra == "evaluation"
Requires-Dist: google-api-python-client>=2.0.0; extra == "evaluation"
Provides-Extra: gpu
Requires-Dist: nvidia-ml-py>=11.495.46; extra == "gpu"
Requires-Dist: codecarbon>=2.3.0; extra == "gpu"
Provides-Extra: amd-gpu
Requires-Dist: amdsmi>=7.0.0; extra == "amd-gpu"
Requires-Dist: codecarbon>=2.3.0; extra == "amd-gpu"
Provides-Extra: all-gpu
Requires-Dist: nvidia-ml-py>=11.495.46; extra == "all-gpu"
Requires-Dist: amdsmi>=7.0.0; extra == "all-gpu"
Requires-Dist: codecarbon>=2.3.0; extra == "all-gpu"
Provides-Extra: co2
Requires-Dist: codecarbon>=2.3.0; extra == "co2"
Provides-Extra: openai
Requires-Dist: openai>=1.0.0; extra == "openai"
Provides-Extra: openrouter
Requires-Dist: openai>=1.0.0; extra == "openrouter"
Provides-Extra: anthropic
Requires-Dist: anthropic>=0.18.0; extra == "anthropic"
Provides-Extra: google
Requires-Dist: google-generativeai>=0.3.0; extra == "google"
Provides-Extra: aws
Requires-Dist: boto3>=1.28.0; extra == "aws"
Provides-Extra: azure
Requires-Dist: azure-ai-openai>=1.0.0; extra == "azure"
Provides-Extra: cohere
Requires-Dist: cohere>=4.0.0; extra == "cohere"
Provides-Extra: mistral
Requires-Dist: mistralai>=0.4.2; extra == "mistral"
Provides-Extra: together
Requires-Dist: together>=0.2.0; extra == "together"
Provides-Extra: groq
Requires-Dist: groq>=0.4.0; extra == "groq"
Provides-Extra: ollama
Requires-Dist: ollama>=0.1.0; extra == "ollama"
Provides-Extra: replicate
Requires-Dist: replicate>=0.15.0; extra == "replicate"
Provides-Extra: sambanova
Requires-Dist: sambanova>=1.0.0; extra == "sambanova"
Provides-Extra: langchain
Requires-Dist: langchain>=0.1.0; extra == "langchain"
Provides-Extra: langgraph
Requires-Dist: langgraph>=0.1.0; extra == "langgraph"
Provides-Extra: llamaindex
Requires-Dist: llama-index>=0.9.0; extra == "llamaindex"
Provides-Extra: huggingface
Requires-Dist: transformers>=4.30.0; extra == "huggingface"
Provides-Extra: crewai
Requires-Dist: crewai>=0.1.0; extra == "crewai"
Provides-Extra: autogen
Requires-Dist: pyautogen>=0.2.0; extra == "autogen"
Provides-Extra: haystack
Requires-Dist: haystack-ai>=2.0.0; extra == "haystack"
Provides-Extra: dspy
Requires-Dist: dspy-ai>=2.0.0; extra == "dspy"
Provides-Extra: guardrails
Requires-Dist: guardrails-ai>=0.4.0; extra == "guardrails"
Provides-Extra: instructor
Requires-Dist: instructor>=1.0.0; extra == "instructor"
Provides-Extra: pydantic-ai
Requires-Dist: pydantic-ai>=0.0.1; extra == "pydantic-ai"
Provides-Extra: vertexai
Requires-Dist: google-cloud-aiplatform>=1.0.0; extra == "vertexai"
Provides-Extra: databases
Requires-Dist: opentelemetry-instrumentation-sqlalchemy>=0.41b0; extra == "databases"
Requires-Dist: sqlalchemy>=1.4.0; extra == "databases"
Requires-Dist: opentelemetry-instrumentation-redis>=0.41b0; extra == "databases"
Requires-Dist: redis; extra == "databases"
Requires-Dist: opentelemetry-instrumentation-pymongo>=0.41b0; extra == "databases"
Requires-Dist: pymongo; extra == "databases"
Requires-Dist: opentelemetry-instrumentation-psycopg2>=0.41b0; extra == "databases"
Requires-Dist: psycopg2-binary>=2.9.0; extra == "databases"
Requires-Dist: opentelemetry-instrumentation-mysql>=0.41b0; extra == "databases"
Requires-Dist: mysql-connector-python>=9.1.0; extra == "databases"
Provides-Extra: messaging
Requires-Dist: opentelemetry-instrumentation-kafka-python>=0.41b0; extra == "messaging"
Requires-Dist: kafka-python; extra == "messaging"
Provides-Extra: vector-dbs
Requires-Dist: pinecone>=3.0.0; extra == "vector-dbs"
Requires-Dist: weaviate-client>=3.0.0; extra == "vector-dbs"
Requires-Dist: qdrant-client>=1.0.0; extra == "vector-dbs"
Requires-Dist: chromadb>=0.4.0; extra == "vector-dbs"
Requires-Dist: pymilvus>=2.3.0; extra == "vector-dbs"
Requires-Dist: faiss-cpu>=1.7.0; extra == "vector-dbs"
Provides-Extra: all-providers
Requires-Dist: openai>=1.0.0; extra == "all-providers"
Requires-Dist: anthropic>=0.18.0; extra == "all-providers"
Requires-Dist: google-generativeai>=0.3.0; extra == "all-providers"
Requires-Dist: boto3>=1.28.0; extra == "all-providers"
Requires-Dist: azure-ai-openai>=1.0.0; extra == "all-providers"
Requires-Dist: cohere>=4.0.0; extra == "all-providers"
Requires-Dist: mistralai>=0.4.2; extra == "all-providers"
Requires-Dist: together>=0.2.0; extra == "all-providers"
Requires-Dist: groq>=0.4.0; extra == "all-providers"
Requires-Dist: ollama>=0.1.0; extra == "all-providers"
Requires-Dist: replicate>=0.15.0; extra == "all-providers"
Requires-Dist: sambanova>=1.0.0; extra == "all-providers"
Requires-Dist: langchain>=0.1.0; extra == "all-providers"
Requires-Dist: langgraph>=0.1.0; extra == "all-providers"
Requires-Dist: llama-index>=0.9.0; extra == "all-providers"
Requires-Dist: transformers>=4.30.0; extra == "all-providers"
Requires-Dist: litellm>=1.0.0; extra == "all-providers"
Requires-Dist: crewai>=0.1.0; extra == "all-providers"
Requires-Dist: pyautogen>=0.2.0; extra == "all-providers"
Requires-Dist: haystack-ai>=2.0.0; extra == "all-providers"
Requires-Dist: dspy-ai>=2.0.0; extra == "all-providers"
Requires-Dist: guardrails-ai>=0.4.0; extra == "all-providers"
Requires-Dist: instructor>=1.0.0; extra == "all-providers"
Requires-Dist: pydantic-ai>=0.0.1; extra == "all-providers"
Requires-Dist: google-cloud-aiplatform>=1.0.0; extra == "all-providers"
Provides-Extra: all-mcp
Requires-Dist: opentelemetry-instrumentation-sqlalchemy>=0.41b0; extra == "all-mcp"
Requires-Dist: opentelemetry-instrumentation-redis>=0.41b0; extra == "all-mcp"
Requires-Dist: opentelemetry-instrumentation-pymongo>=0.41b0; extra == "all-mcp"
Requires-Dist: opentelemetry-instrumentation-psycopg2>=0.41b0; extra == "all-mcp"
Requires-Dist: opentelemetry-instrumentation-mysql>=0.41b0; extra == "all-mcp"
Requires-Dist: opentelemetry-instrumentation-kafka-python>=0.41b0; extra == "all-mcp"
Requires-Dist: pinecone>=3.0.0; extra == "all-mcp"
Requires-Dist: weaviate-client>=3.0.0; extra == "all-mcp"
Requires-Dist: qdrant-client>=1.0.0; extra == "all-mcp"
Requires-Dist: chromadb>=0.4.0; extra == "all-mcp"
Requires-Dist: pymilvus>=2.3.0; extra == "all-mcp"
Requires-Dist: faiss-cpu>=1.7.0; extra == "all-mcp"
Requires-Dist: sqlalchemy; extra == "all-mcp"
Provides-Extra: all
Requires-Dist: openai>=1.0.0; extra == "all"
Requires-Dist: anthropic>=0.18.0; extra == "all"
Requires-Dist: google-generativeai>=0.3.0; extra == "all"
Requires-Dist: boto3>=1.28.0; extra == "all"
Requires-Dist: azure-ai-openai>=1.0.0; extra == "all"
Requires-Dist: cohere>=4.0.0; extra == "all"
Requires-Dist: mistralai>=0.4.2; extra == "all"
Requires-Dist: together>=0.2.0; extra == "all"
Requires-Dist: groq>=0.4.0; extra == "all"
Requires-Dist: ollama>=0.1.0; extra == "all"
Requires-Dist: replicate>=0.15.0; extra == "all"
Requires-Dist: sambanova>=1.0.0; extra == "all"
Requires-Dist: langchain>=0.1.0; extra == "all"
Requires-Dist: langgraph>=0.1.0; extra == "all"
Requires-Dist: llama-index>=0.9.0; extra == "all"
Requires-Dist: transformers>=4.30.0; extra == "all"
Requires-Dist: nvidia-ml-py>=11.495.46; extra == "all"
Requires-Dist: amdsmi>=7.0.0; extra == "all"
Requires-Dist: codecarbon>=2.3.0; extra == "all"
Requires-Dist: crewai>=0.1.0; extra == "all"
Requires-Dist: pyautogen>=0.2.0; extra == "all"
Requires-Dist: haystack-ai>=2.0.0; extra == "all"
Requires-Dist: dspy-ai>=2.0.0; extra == "all"
Requires-Dist: guardrails-ai>=0.4.0; extra == "all"
Requires-Dist: instructor>=1.0.0; extra == "all"
Requires-Dist: pydantic-ai>=0.0.1; extra == "all"
Requires-Dist: google-cloud-aiplatform>=1.0.0; extra == "all"
Requires-Dist: opentelemetry-instrumentation-sqlalchemy>=0.41b0; extra == "all"
Requires-Dist: opentelemetry-instrumentation-redis>=0.41b0; extra == "all"
Requires-Dist: opentelemetry-instrumentation-pymongo>=0.41b0; extra == "all"
Requires-Dist: opentelemetry-instrumentation-psycopg2>=0.41b0; extra == "all"
Requires-Dist: opentelemetry-instrumentation-mysql>=0.41b0; extra == "all"
Requires-Dist: opentelemetry-instrumentation-kafka-python>=0.41b0; extra == "all"
Requires-Dist: pinecone>=3.0.0; extra == "all"
Requires-Dist: weaviate-client>=3.0.0; extra == "all"
Requires-Dist: qdrant-client>=1.0.0; extra == "all"
Requires-Dist: chromadb>=0.4.0; extra == "all"
Requires-Dist: pymilvus>=2.3.0; extra == "all"
Requires-Dist: faiss-cpu>=1.7.0; extra == "all"
Requires-Dist: sqlalchemy; extra == "all"
Requires-Dist: presidio-analyzer>=2.2.0; extra == "all"
Requires-Dist: presidio-anonymizer>=2.2.0; extra == "all"
Requires-Dist: spacy>=3.0.0; extra == "all"
Requires-Dist: detoxify>=0.5.0; extra == "all"
Requires-Dist: google-api-python-client>=2.0.0; extra == "all"
Provides-Extra: dev
Requires-Dist: pytest>=7.0.0; extra == "dev"
Requires-Dist: pytest-cov>=4.0.0; extra == "dev"
Requires-Dist: pytest-mock>=3.10.0; extra == "dev"
Requires-Dist: pytest-asyncio>=0.21.0; extra == "dev"
Requires-Dist: black>=23.0.0; extra == "dev"
Requires-Dist: isort>=5.12.0; extra == "dev"
Requires-Dist: pylint>=2.17.0; extra == "dev"
Requires-Dist: mypy>=1.0.0; extra == "dev"
Requires-Dist: build>=0.10.0; extra == "dev"
Requires-Dist: twine>=4.0.0; extra == "dev"
Dynamic: license-file
